{
    "id": "subrace_gnome_rock",
    "name": "Rock Gnome",
    "parentRaceId": "race_gnome",
    "lore": {
        "shortDescription": "You have a natural inventiveness and hardiness beyond that of other gnomes.",
        "fullText": "As a rock gnome, you have a natural inventiveness and hardiness beyond that of other gnomes. Most gnomes in the worlds of D&D are rock gnomes, including the tinker gnomes of the Dragonlance setting."
    },
    "traitsAdded": [
        "trait_gnome_rock_ability_bonuses",
        "trait_artificers_lore",
        "trait_tinker"
    ]
}